earthquake_data/__init__.py
earthquake_recent/__init__.py
get_data_earthquake_indonesia-0.1.dist-info/LICENSE
get_data_earthquake_indonesia-0.1.dist-info/METADATA
get_data_earthquake_indonesia-0.1.dist-info/WHEEL
get_data_earthquake_indonesia-0.1.dist-info/top_level.txt
get_data_earthquake_indonesia-0.1.dist-info/RECORD
