Metadata-Version: 2.1
Name: get-data-earthquake-indonesia
Version: 0.1
Summary: This is will get the latest information of earthquake in Indonesia (BMKG.go.id)
Home-page: https://github.com/Miqbal20/latest-indonesia-earthquake-information
Author: Muhammad Iqbal
Author-email: miqbal020@hotmail.com
License: UNKNOWN
Project-URL: Website, https://replit.com/@miqbal20
Platform: UNKNOWN
Classifier: Programming Language :: Python :: 3
Classifier: License :: OSI Approved :: GNU General Public License v3 (GPLv3)
Classifier: Operating System :: OS Independent
Classifier: Development Status :: 4 - Beta
Requires-Python: >=3.6
License-File: LICENSE
